sphinx_problog/__init__.py
sphinx_problog/problog.py
sphinx_problog/_static/README.md
sphinx_problog/_static/ace.js
sphinx_problog/_static/jquery-fix.js
sphinx_problog/_static/mode-problog.js
sphinx_problog/_static/problog_editor_advanced.js
sphinx_problog/_static/sphinx-problog.css
sphinx_problog-0.1.post4.dist-info/LICENCE
sphinx_problog-0.1.post4.dist-info/METADATA
sphinx_problog-0.1.post4.dist-info/WHEEL
sphinx_problog-0.1.post4.dist-info/top_level.txt
sphinx_problog-0.1.post4.dist-info/RECORD
