Metadata-Version: 2.1
Name: sphinx-problog
Version: 0.1.post4
Summary: A collection of Sphinx (and Jupyter Book) extensions for authoring interactive ProbLog code blocks.
Home-page: https://github.com/simply-logical/sphinx-problog
Maintainer: Kacper Sokol
Maintainer-email: k.sokol@bristol.ac.uk
License: new BSD
Download-URL: https://pypi.org/project/sphinx-problog/#files
Platform: UNKNOWN
Requires-Python: ~=3.5
Requires-Dist: docutils
Requires-Dist: sphinx (>=3)
